fracx/__init__.py
fracx/__main__.py
fracx/__version__.py
fracx/api/mixins.py
fracx/api/models.py
fracx/collector/__init__.py
fracx/collector/collector.py
fracx/collector/downloader.py
fracx/collector/endpoint.py
fracx/collector/filehandler.py
fracx/collector/parser.py
fracx/collector/row_parser.py
fracx/collector/transformer.py
fracx/collector/yammler.py
fracx/config.py
fracx/data_files/collector.yaml
fracx/data_files/init.pgsql
fracx/data_files/init.sql
fracx/data_files/parsers.yaml
fracx/loggers.py
fracx/manage.py
fracx/metrics/__init__.py
fracx/metrics/metrics.py
fracx/util/__init__.py
fracx/util/deco.py
fracx/util/exc.py
fracx/util/jsontools.py
fracx/util/strings.py
fracx/wsgi.py
fracx-0.1.16.dist-info/entry_points.txt
fracx-0.1.16.dist-info/LICENSE
fracx-0.1.16.dist-info/WHEEL
fracx-0.1.16.dist-info/METADATA
fracx-0.1.16.dist-info/RECORD
