Metadata-Version: 2.1
Name: fracx
Version: 0.1.16
Summary: FracX is a library that can be used to interface with PDS Energy's FracX platform for exchanging frac schedules.
Home-page: https://github.com/la-mar/permian-frac-exchange
License: MIT
Keywords: fracx,frac,oil,gas
Author: Brock Friedrich
Author-email: brocklfriedrich@gmail.com
Requires-Python: >=3.6.5,<4.0.0
Classifier: License :: OSI Approved :: MIT License
Classifier: Programming Language :: Python :: 3
Classifier: Programming Language :: Python :: 3.7
Classifier: Programming Language :: Python :: 3.8
Provides-Extra: mssql
Requires-Dist: aiocontextvars (>=0.2.2,<0.3.0)
Requires-Dist: attr (>=0.3.1,<0.4.0)
Requires-Dist: attrdict (>=2.0.1,<3.0.0)
Requires-Dist: attrs (>=19.3.0,<20.0.0)
Requires-Dist: click (>=7.0,<8.0)
Requires-Dist: colorama (>=0.4.3,<0.5.0)
Requires-Dist: coverage[toml] (>=5.0.2,<6.0.0)
Requires-Dist: cython (>=0.29.14,<0.30.0); extra == "mssql"
Requires-Dist: datadog (>=0.33.0,<0.34.0)
Requires-Dist: flask-sqlalchemy (>=2.4.1,<3.0.0)
Requires-Dist: json_log_formatter (>=0.2.0,<0.3.0)
Requires-Dist: logutils (>=0.3.5,<0.4.0)
Requires-Dist: psycopg2-binary (>=2.8.4,<3.0.0)
Requires-Dist: pymssql (>=2.1.4,<3.0.0); extra == "mssql"
Requires-Dist: pyparsing (>=2.4.6,<3.0.0)
Requires-Dist: python-dateutil (>=2.8.1,<3.0.0)
Requires-Dist: python-dotenv (>=0.10.3,<0.11.0)
Requires-Dist: pyyaml (>=5.2,<6.0)
Requires-Dist: sqlalchemy (>=1.3.12,<2.0.0)
Requires-Dist: tomlkit (>=0.5.8,<0.6.0)
Requires-Dist: xlrd (>=1.2.0,<2.0.0)
Project-URL: Repository, https://github.com/la-mar/permian-frac-exchange
